get_cosmopower_emus/__init__.py
get_cosmopower_emus/get_cosmopower_emus.py
get_cosmopower_emus-0.0.16.dist-info/METADATA
get_cosmopower_emus-0.0.16.dist-info/WHEEL
get_cosmopower_emus-0.0.16.dist-info/top_level.txt
get_cosmopower_emus-0.0.16.dist-info/RECORD
