Metadata-Version: 2.1
Name: get_cosmopower_emus
Version: 0.0.16
Summary: Package to download Cosmopower emulators.
Maintainer-email: Boris Bolliet <bb667@cam.ac.uk>
License: MIT
Project-URL: Homepage, https://github.com/CLASS-SZ
Project-URL: GitHub, https://github.com/CLASS-SZ
